MANIFEST.in
README.md
setup.cfg
setup.py
versioneer.py
pymodeler/__init__.py
pymodeler/_version.py
pymodeler/model.py
pymodeler/parameter.py
pymodeler.egg-info/PKG-INFO
pymodeler.egg-info/SOURCES.txt
pymodeler.egg-info/dependency_links.txt
pymodeler.egg-info/requires.txt
pymodeler.egg-info/top_level.txt