Metadata-Version: 1.1
Name: pymodeler
Version: 0.1.4
Summary: Infrastructure for creating parametrized models in python.
Home-page: https://github.com/kadrlica/pymodeler
Author: Alex Drlica-Wagner
Author-email: kadrlica@fnal.gov
License: UNKNOWN
Platform: any
Classifier: Development Status :: 2 - Pre-Alpha
Classifier: Intended Audience :: Science/Research
Classifier: Intended Audience :: Developers
Classifier: Programming Language :: Python
Classifier: Programming Language :: Python :: 2
Classifier: Programming Language :: Python :: 2.7
Classifier: Programming Language :: Python :: 3
Classifier: Programming Language :: Python :: 3.4
Classifier: Natural Language :: English
Classifier: Topic :: Scientific/Engineering
